fridex_connection-0.0.1-py3.11-nspkg.pth
fridex/connection/__init__.py
fridex/connection/communication/__init__.py
fridex/connection/communication/_base_connection.py
fridex/connection/communication/_client_connection.py
fridex/connection/communication/_client_handler.py
fridex/connection/communication/_server_connection.py
fridex/connection/communication/_test_base_connection.py
fridex/connection/communication/_test_communication.py
fridex/connection/encryption/__init__.py
fridex/connection/encryption/_cryption.py
fridex/connection/encryption/_cryption_method.py
fridex/connection/encryption/_fernet.py
fridex/connection/encryption/_private_public.py
fridex/connection/encryption/_supertest_cryption.py
fridex/connection/encryption/_test_fernet.py
fridex/connection/encryption/_test_private_public.py
fridex/connection/protocol/__init__.py
fridex/connection/protocol/_cache.py
fridex/connection/protocol/_communication.py
fridex/connection/protocol/_control.py
fridex/connection/protocol/_data.py
fridex/connection/protocol/_protocol.py
fridex/connection/protocol/_protocol_interface.py
fridex/connection/protocol/_subscription.py
fridex/connection/protocol/_types.py
fridex_connection-0.0.1.dist-info/LICENSE
fridex_connection-0.0.1.dist-info/METADATA
fridex_connection-0.0.1.dist-info/WHEEL
fridex_connection-0.0.1.dist-info/namespace_packages.txt
fridex_connection-0.0.1.dist-info/top_level.txt
fridex_connection-0.0.1.dist-info/RECORD
